2016-01-24 23:21:49-----------------出错啦-----------------,PayType=recharge,Status=0000000099\r\n2016-01-24 23:21:49<xml><appid><![CDATA[wx06dcafb051f5e21f]]></appid>
<attach><![CDATA[cky16012411212664827]]></attach>
<bank_type><![CDATA[CFT]]></bank_type>
<cash_fee><![CDATA[1]]></cash_fee>
<fee_type><![CDATA[CNY]]></fee_type>
<is_subscribe><![CDATA[Y]]></is_subscribe>
<mch_id><![CDATA[1292995201]]></mch_id>
<nonce_str><![CDATA[36hnqj5nfca1lbiaod5hdkz05sk1nz9z]]></nonce_str>
<openid><![CDATA[o4CBRwu4gN7w8JZsVCw6leu9g2-Y]]></openid>
<out_trade_no><![CDATA[129299520120160124232126]]></out_trade_no>
<result_code><![CDATA[SUCCESS]]></result_code>
<return_code><![CDATA[SUCCESS]]></return_code>
<sign><![CDATA[5562BA815F50F1B0B01431F8DD32ECF5]]></sign>
<time_end><![CDATA[20160124232134]]></time_end>
<total_fee>1</total_fee>
<trade_type><![CDATA[JSAPI]]></trade_type>
<transaction_id><![CDATA[1008850043201601242883310337]]></transaction_id>
</xml>\r\n2016-01-24 23:33:1710=10,$pageNum=1,$type=0\r\n2016-01-24 23:33:2010=10,$pageNum=1,$type=1\r\n2016-01-24 23:33:2110=10,$pageNum=1,$type=1\r\n2016-01-24 23:34:4610=10,$pageNum=1,$type=1\r\n2016-01-24 23:34:4910=10,$pageNum=1,$type=1\r\n2016-01-24 23:37:4710=10,$pageNum=1,$type=0\r\n2016-01-24 23:37:5010=10,$pageNum=1,$type=1\r\n2016-01-24 23:38:0010=10,$pageNum=1,$type=1\r\n2016-01-24 23:44:2710=10,$pageNum=1,$type=\r\n2016-01-24 23:44:3410=10,$pageNum=1,$type=\r\n2016-01-24 23:44:3510=10,$pageNum=1,$type=\r\n